Workbook

Sheet Record
G1: ใส่เงินลงทุนเริ่มต้น >>>>>>>> | K1: 15000 | M1: Play 4H
A2: Open | F2: Close | I2: Gain | K2: Loss | M2: Feedback | O2: Score Board
A3: Date | B3: Order | C3: Side | D3: Price | E3: Volume | F3: Price | I3: จุด | J3: Amount | K3: จุด | L3: Amount | O3: Accuracy & Gain/Loss perform
A4: 17/3/2026 | B4: 1 | C4: L | D4: 929 | E4: 1 | F4: 944.5 | I4: =IF(C4="L",IF(F4-D4>0,F4-D4," "),IF(D4-F4>0,D4-F4," ")) -> 15.5 | J4: =IF(C4="L",IF(F4-D4>0,(F4-D4)*200*E4," "),IF(D4-F4>0,(D4-F4)*200*E4," ")) -> 3100 | K4: =IF(C4="L",IF(F4-D4<0,F4-D4," "),IF(D4-F4<0,D4-F4," ")) | L4: =IF(C4="L",IF(F4-D4<0,(F4-D4)*200*E4," "),IF(D4-F4<0,(D4-F4)*200*E4," ")) | N4: M | O4: Total Trade | P4: =B29+C29 -> 1
B5: 2 | I5: =IF(C5="L",IF(F5-D5>0,F5-D5," "),IF(D5-F5>0,D5-F5," ")) | J5: =IF(C5="L",IF(F5-D5>0,(F5-D5)*200*E5," "),IF(D5-F5>0,(D5-F5)*200*E5," ")) | K5: =IF(C5="L",IF(F5-D5<0,F5-D5," "),IF(D5-F5<0,D5-F5," ")) | L5: =IF(C5="L",IF(F5-D5<0,(F5-D5)*200*E5," "),IF(D5-F5<0,(D5-F5)*200*E5," ")) | O5: Winning Chance | P5: =B29/P4*100 -> 100 | Q5: Loss Chance | R5: =C29/P4*100 -> 0
B6: 3 | I6: =IF(C6="L",IF(F6-D6>0,F6-D6," "),IF(D6-F6>0,D6-F6," ")) | J6: =IF(C6="L",IF(F6-D6>0,(F6-D6)*200*E6," "),IF(D6-F6>0,(D6-F6)*200*E6," ")) | K6: =IF(C6="L",IF(F6-D6<0,F6-D6," "),IF(D6-F6<0,D6-F6," ")) | L6: =IF(C6="L",IF(F6-D6<0,(F6-D6)*200*E6," "),IF(D6-F6<0,(D6-F6)*200*E6," ")) | O6: Average Gain | P6: =SUM(I5:I28)/B29 -> 0 | Q6: Average Loss | R6: =SUM(K5:K28)/C29 -> #DIV/0!
B7: 4 | I7: =IF(C7="L",IF(F7-D7>0,F7-D7," "),IF(D7-F7>0,D7-F7," ")) | J7: =IF(C7="L",IF(F7-D7>0,(F7-D7)*200*E7," "),IF(D7-F7>0,(D7-F7)*200*E7," ")) | K7: =IF(C7="L",IF(F7-D7<0,F7-D7," "),IF(D7-F7<0,D7-F7," ")) | L7: =IF(C7="L",IF(F7-D7<0,(F7-D7)*200*E7," "),IF(D7-F7<0,(D7-F7)*200*E7," ")) | O7: Total Gain | P7: =SUM(J4:J28) -> 3100 | Q7: Total Loss | R7: =SUM(L4:L28) -> 0
B8: 5 | I8: =IF(C8="L",IF(F8-D8>0,F8-D8," "),IF(D8-F8>0,D8-F8," ")) | J8: =IF(C8="L",IF(F8-D8>0,(F8-D8)*200*E8," "),IF(D8-F8>0,(D8-F8)*200*E8," ")) | K8: =IF(C8="L",IF(F8-D8<0,F8-D8," "),IF(D8-F8<0,D8-F8," ")) | L8: =IF(C8="L",IF(F8-D8<0,(F8-D8)*200*E8," "),IF(D8-F8<0,(D8-F8)*200*E8," ")) | O8: Performance
B9: 6 | I9: =IF(C9="L",IF(F9-D9>0,F9-D9," "),IF(D9-F9>0,D9-F9," ")) | J9: =IF(C9="L",IF(F9-D9>0,(F9-D9)*200*E9," "),IF(D9-F9>0,(D9-F9)*200*E9," ")) | K9: =IF(C9="L",IF(F9-D9<0,F9-D9," "),IF(D9-F9<0,D9-F9," ")) | L9: =IF(C9="L",IF(F9-D9<0,(F9-D9)*200*E9," "),IF(D9-F9<0,(D9-F9)*200*E9," ")) | O9: Net Profit | P9: =P7+R7-K30 -> 3067.9 | Q9: Cost rate | R9: =K30/P9 -> 0.010463183
B10: 7 | I10: =IF(C10="L",IF(F10-D10>0,F10-D10," "),IF(D10-F10>0,D10-F10," ")) | J10: =IF(C10="L",IF(F10-D10>0,(F10-D10)*200*E10," "),IF(D10-F10>0,(D10-F10)*200*E10," ")) | K10: =IF(C10="L",IF(F10-D10<0,F10-D10," "),IF(D10-F10<0,D10-F10," ")) | L10: =IF(C10="L",IF(F10-D10<0,(F10-D10)*200*E10," "),IF(D10-F10<0,(D10-F10)*200*E10," "))
B11: 8 | I11: =IF(C11="L",IF(F11-D11>0,F11-D11," "),IF(D11-F11>0,D11-F11," ")) | J11: =IF(C11="L",IF(F11-D11>0,(F11-D11)*200*E11," "),IF(D11-F11>0,(D11-F11)*200*E11," ")) | K11: =IF(C11="L",IF(F11-D11<0,F11-D11," "),IF(D11-F11<0,D11-F11," ")) | L11: =IF(C11="L",IF(F11-D11<0,(F11-D11)*200*E11," "),IF(D11-F11<0,(D11-F11)*200*E11," ")) | O11: Expected Return | R11: =IF(R7<0,((P5*P6/100)+(R5*R6/100)),P6) -> 0
B12: 9 | I12: =IF(C12="L",IF(F12-D12>0,F12-D12," "),IF(D12-F12>0,D12-F12," ")) | J12: =IF(C12="L",IF(F12-D12>0,(F12-D12)*200*E12," "),IF(D12-F12>0,(D12-F12)*200*E12," ")) | K12: =IF(C12="L",IF(F12-D12<0,F12-D12," "),IF(D12-F12<0,D12-F12," ")) | L12: =IF(C12="L",IF(F12-D12<0,(F12-D12)*200*E12," "),IF(D12-F12<0,(D12-F12)*200*E12," "))
B13: 10 | I13: =IF(C13="L",IF(F13-D13>0,F13-D13," "),IF(D13-F13>0,D13-F13," ")) | J13: =IF(C13="L",IF(F13-D13>0,(F13-D13)*200*E13," "),IF(D13-F13>0,(D13-F13)*200*E13," ")) | K13: =IF(C13="L",IF(F13-D13<0,F13-D13," "),IF(D13-F13<0,D13-F13," ")) | L13: =IF(C13="L",IF(F13-D13<0,(F13-D13)*200*E13," "),IF(D13-F13<0,(D13-F13)*200*E13," "))
B14: 11 | I14: =IF(C14="L",IF(F14-D14>0,F14-D14," "),IF(D14-F14>0,D14-F14," ")) | J14: =IF(C14="L",IF(F14-D14>0,(F14-D14)*200*E14," "),IF(D14-F14>0,(D14-F14)*200*E14," ")) | K14: =IF(C14="L",IF(F14-D14<0,F14-D14," "),IF(D14-F14<0,D14-F14," ")) | L14: =IF(C14="L",IF(F14-D14<0,(F14-D14)*200*E14," "),IF(D14-F14<0,(D14-F14)*200*E14," ")) | O14: Top Ranking
B15: 12 | I15: =IF(C15="L",IF(F15-D15>0,F15-D15," "),IF(D15-F15>0,D15-F15," ")) | J15: =IF(C15="L",IF(F15-D15>0,(F15-D15)*200*E15," "),IF(D15-F15>0,(D15-F15)*200*E15," ")) | K15: =IF(C15="L",IF(F15-D15<0,F15-D15," "),IF(D15-F15<0,D15-F15," ")) | L15: =IF(C15="L",IF(F15-D15<0,(F15-D15)*200*E15," "),IF(D15-F15<0,(D15-F15)*200*E15," ")) | O15: Best Gain | P15: =MAX(I5:I28) -> 0 | R15: =P15-P17 -> 0
B16: 13 | I16: =IF(C16="L",IF(F16-D16>0,F16-D16," "),IF(D16-F16>0,D16-F16," ")) | J16: =IF(C16="L",IF(F16-D16>0,(F16-D16)*200*E16," "),IF(D16-F16>0,(D16-F16)*200*E16," ")) | K16: =IF(C16="L",IF(F16-D16<0,F16-D16," "),IF(D16-F16<0,D16-F16," ")) | L16: =IF(C16="L",IF(F16-D16<0,(F16-D16)*200*E16," "),IF(D16-F16<0,(D16-F16)*200*E16," ")) | O16: Best Gain Amount | P16: =MAX(J4:J28) -> 3100
B17: 14 | I17: =IF(C17="L",IF(F17-D17>0,F17-D17," "),IF(D17-F17>0,D17-F17," ")) | J17: =IF(C17="L",IF(F17-D17>0,(F17-D17)*200*E17," "),IF(D17-F17>0,(D17-F17)*200*E17," ")) | K17: =IF(C17="L",IF(F17-D17<0,F17-D17," "),IF(D17-F17<0,D17-F17," ")) | L17: =IF(C17="L",IF(F17-D17<0,(F17-D17)*200*E17," "),IF(D17-F17<0,(D17-F17)*200*E17," ")) | O17: Bad Loss | P17: =MIN(K5:K28) -> 0
B18: 15 | I18: =IF(C18="L",IF(F18-D18>0,F18-D18," "),IF(D18-F18>0,D18-F18," ")) | J18: =IF(C18="L",IF(F18-D18>0,(F18-D18)*200*E18," "),IF(D18-F18>0,(D18-F18)*200*E18," ")) | K18: =IF(C18="L",IF(F18-D18<0,F18-D18," "),IF(D18-F18<0,D18-F18," ")) | L18: =IF(C18="L",IF(F18-D18<0,(F18-D18)*200*E18," "),IF(D18-F18<0,(D18-F18)*200*E18," ")) | O18: Bad Loss Amount | P18: =MIN(L4:L28) -> 0
B19: 16 | I19: =IF(C19="L",IF(F19-D19>0,F19-D19," "),IF(D19-F19>0,D19-F19," ")) | J19: =IF(C19="L",IF(F19-D19>0,(F19-D19)*200*E19," "),IF(D19-F19>0,(D19-F19)*200*E19," ")) | K19: =IF(C19="L",IF(F19-D19<0,F19-D19," "),IF(D19-F19<0,D19-F19," ")) | L19: =IF(C19="L",IF(F19-D19<0,(F19-D19)*200*E19," "),IF(D19-F19<0,(D19-F19)*200*E19," "))
B20: 17 | I20: =IF(C20="L",IF(F20-D20>0,F20-D20," "),IF(D20-F20>0,D20-F20," ")) | J20: =IF(C20="L",IF(F20-D20>0,(F20-D20)*200*E20," "),IF(D20-F20>0,(D20-F20)*200*E20," ")) | K20: =IF(C20="L",IF(F20-D20<0,F20-D20," "),IF(D20-F20<0,D20-F20," ")) | L20: =IF(C20="L",IF(F20-D20<0,(F20-D20)*200*E20," "),IF(D20-F20<0,(D20-F20)*200*E20," "))
B21: 18 | I21: =IF(C21="L",IF(F21-D21>0,F21-D21," "),IF(D21-F21>0,D21-F21," ")) | J21: =IF(C21="L",IF(F21-D21>0,(F21-D21)*200*E21," "),IF(D21-F21>0,(D21-F21)*200*E21," ")) | K21: =IF(C21="L",IF(F21-D21<0,F21-D21," "),IF(D21-F21<0,D21-F21," ")) | L21: =IF(C21="L",IF(F21-D21<0,(F21-D21)*200*E21," "),IF(D21-F21<0,(D21-F21)*200*E21," "))
B22: 19 | I22: =IF(C22="L",IF(F22-D22>0,F22-D22," "),IF(D22-F22>0,D22-F22," ")) | J22: =IF(C22="L",IF(F22-D22>0,(F22-D22)*200*E22," "),IF(D22-F22>0,(D22-F22)*200*E22," ")) | K22: =IF(C22="L",IF(F22-D22<0,F22-D22," "),IF(D22-F22<0,D22-F22," ")) | L22: =IF(C22="L",IF(F22-D22<0,(F22-D22)*200*E22," "),IF(D22-F22<0,(D22-F22)*200*E22," "))
B23: 20 | I23: =IF(C23="L",IF(F23-D23>0,F23-D23," "),IF(D23-F23>0,D23-F23," ")) | J23: =IF(C23="L",IF(F23-D23>0,(F23-D23)*200*E23," "),IF(D23-F23>0,(D23-F23)*200*E23," ")) | K23: =IF(C23="L",IF(F23-D23<0,F23-D23," "),IF(D23-F23<0,D23-F23," ")) | L23: =IF(C23="L",IF(F23-D23<0,(F23-D23)*200*E23," "),IF(D23-F23<0,(D23-F23)*200*E23," "))
B24: 21 | I24: =IF(C24="L",IF(F24-D24>0,F24-D24," "),IF(D24-F24>0,D24-F24," ")) | J24: =IF(C24="L",IF(F24-D24>0,(F24-D24)*200*E24," "),IF(D24-F24>0,(D24-F24)*200*E24," ")) | K24: =IF(C24="L",IF(F24-D24<0,F24-D24," "),IF(D24-F24<0,D24-F24," ")) | L24: =IF(C24="L",IF(F24-D24<0,(F24-D24)*200*E24," "),IF(D24-F24<0,(D24-F24)*200*E24," "))
B25: 22 | I25: =IF(C25="L",IF(F25-D25>0,F25-D25," "),IF(D25-F25>0,D25-F25," ")) | J25: =IF(C25="L",IF(F25-D25>0,(F25-D25)*200*E25," "),IF(D25-F25>0,(D25-F25)*200*E25," ")) | K25: =IF(C25="L",IF(F25-D25<0,F25-D25," "),IF(D25-F25<0,D25-F25," ")) | L25: =IF(C25="L",IF(F25-D25<0,(F25-D25)*200*E25," "),IF(D25-F25<0,(D25-F25)*200*E25," "))
B26: 23 | I26: =IF(C26="L",IF(F26-D26>0,F26-D26," "),IF(D26-F26>0,D26-F26," ")) | J26: =IF(C26="L",IF(F26-D26>0,(F26-D26)*200*E26," "),IF(D26-F26>0,(D26-F26)*200*E26," ")) | K26: =IF(C26="L",IF(F26-D26<0,F26-D26," "),IF(D26-F26<0,D26-F26," ")) | L26: =IF(C26="L",IF(F26-D26<0,(F26-D26)*200*E26," "),IF(D26-F26<0,(D26-F26)*200*E26," "))
B27: 24 | I27: =IF(C27="L",IF(F27-D27>0,F27-D27," "),IF(D27-F27>0,D27-F27," ")) | J27: =IF(C27="L",IF(F27-D27>0,(F27-D27)*200*E27," "),IF(D27-F27>0,(D27-F27)*200*E27," ")) | K27: =IF(C27="L",IF(F27-D27<0,F27-D27," "),IF(D27-F27<0,D27-F27," ")) | L27: =IF(C27="L",IF(F27-D27<0,(F27-D27)*200*E27," "),IF(D27-F27<0,(D27-F27)*200*E27," "))
B28: 25 | I28: =IF(C28="L",IF(F28-D28>0,F28-D28," "),IF(D28-F28>0,D28-F28," ")) | J28: =IF(C28="L",IF(F28-D28>0,(F28-D28)*200*E28," "),IF(D28-F28>0,(D28-F28)*200*E28," ")) | K28: =IF(C28="L",IF(F28-D28<0,F28-D28," "),IF(D28-F28<0,D28-F28," ")) | L28: =IF(C28="L",IF(F28-D28<0,(F28-D28)*200*E28," "),IF(D28-F28<0,(D28-F28)*200*E28," "))
A29: calculate | B29: =COUNT(I4:I28) -> 1 | C29: =COUNT(K4:K28) -> 0 | D29: =SUM(E4:E28)*2 -> 2 | I29: Commission per CON | K29: Com & Vat
I30: 15 | K30: =I30*D29*1.07 -> 32.1
A34: Open | F34: Close | I34: Gain | K34: Loss | O34: Score Board
A35: Date | B35: Order | C35: Side | D35: Price | E35: Volume | F35: Price | I35: จุด | J35: Amount | K35: จุด | L35: Amount | O35: Accuracy & Gain/Loss perform
A36: 45963 | B36: 1 | I36: =IF(C36="L",IF(F36-D36>0,F36-D36," "),IF(D36-F36>0,D36-F36," ")) | J36: =IF(C36="L",IF(F36-D36>0,(F36-D36)*200*E36," "),IF(D36-F36>0,(D36-F36)*200*E36," ")) | K36: =IF(C36="L",IF(F36-D36<0,F36-D36," "),IF(D36-F36<0,D36-F36," ")) | L36: =IF(C36="L",IF(F36-D36<0,(F36-D36)*200*E36," "),IF(D36-F36<0,(D36-F36)*200*E36," ")) | O36: Total Trade | P36: =B61+C61 -> 0
B37: 2 | I37: =IF(C37="L",IF(F37-D37>0,F37-D37," "),IF(D37-F37>0,D37-F37," ")) | J37: =IF(C37="L",IF(F37-D37>0,(F37-D37)*200*E37," "),IF(D37-F37>0,(D37-F37)*200*E37," ")) | L37: =IF(C37="L",IF(F37-D37<0,(F37-D37)*200*E37," "),IF(D37-F37<0,(D37-F37)*200*E37," ")) | O37: Winning Chance | P37: =B61/P36*100 -> #DIV/0! | Q37: Loss Chance | R37: =C61/P36*100 -> #DIV/0!
B38: 3 | I38: =IF(C38="L",IF(F38-D38>0,F38-D38," "),IF(D38-F38>0,D38-F38," ")) | J38: =IF(C38="L",IF(F38-D38>0,(F38-D38)*200*E38," "),IF(D38-F38>0,(D38-F38)*200*E38," ")) | K38: =IF(C37="L",IF(F37-D37<0,F37-D37," "),IF(D37-F37<0,D37-F37," ")) | L38: =IF(C38="L",IF(F38-D38<0,(F38-D38)*200*E38," "),IF(D38-F38<0,(D38-F38)*200*E38," ")) | O38: Average Gain | P38: =SUM(I36:I60)/B61 -> #DIV/0! | Q38: Average Loss | R38: =SUM(K36:K60)/C61 -> #DIV/0!
B39: 4 | I39: =IF(C39="L",IF(F39-D39>0,F39-D39," "),IF(D39-F39>0,D39-F39," ")) | J39: =IF(C39="L",IF(F39-D39>0,(F39-D39)*200*E39," "),IF(D39-F39>0,(D39-F39)*200*E39," ")) | K39: =IF(C39="L",IF(F39-D39<0,F39-D39," "),IF(D39-F39<0,D39-F39," ")) | L39: =IF(C39="L",IF(F39-D39<0,(F39-D39)*200*E39," "),IF(D39-F39<0,(D39-F39)*200*E39," ")) | O39: Total Gain | P39: =SUM(J36:J60) -> 0 | Q39: Total Loss | R39: =SUM(L36:L60) -> 0
B40: 5 | I40: =IF(C40="L",IF(F40-D40>0,F40-D40," "),IF(D40-F40>0,D40-F40," ")) | J40: =IF(C40="L",IF(F40-D40>0,(F40-D40)*200*E40," "),IF(D40-F40>0,(D40-F40)*200*E40," ")) | K40: =IF(C40="L",IF(F40-D40<0,F40-D40," "),IF(D40-F40<0,D40-F40," ")) | L40: =IF(C40="L",IF(F40-D40<0,(F40-D40)*200*E40," "),IF(D40-F40<0,(D40-F40)*200*E40," ")) | O40: Performance
B41: 6 | I41: =IF(C41="L",IF(F41-D41>0,F41-D41," "),IF(D41-F41>0,D41-F41," ")) | J41: =IF(C41="L",IF(F41-D41>0,(F41-D41)*200*E41," "),IF(D41-F41>0,(D41-F41)*200*E41," ")) | K41: =IF(C41="L",IF(F41-D41<0,F41-D41," "),IF(D41-F41<0,D41-F41," ")) | L41: =IF(C41="L",IF(F41-D41<0,(F41-D41)*200*E41," "),IF(D41-F41<0,(D41-F41)*200*E41," ")) | O41: Net Profit | P41: =P39+R39-K62 -> 0 | Q41: Cost rate | R41: =K62/P41 -> #DIV/0!
B42: 7 | I42: =IF(C42="L",IF(F42-D42>0,F42-D42," "),IF(D42-F42>0,D42-F42," ")) | J42: =IF(C42="L",IF(F42-D42>0,(F42-D42)*200*E42," "),IF(D42-F42>0,(D42-F42)*200*E42," ")) | K42: =IF(C42="L",IF(F42-D42<0,F42-D42," "),IF(D42-F42<0,D42-F42," ")) | L42: =IF(C42="L",IF(F42-D42<0,(F42-D42)*200*E42," "),IF(D42-F42<0,(D42-F42)*200*E42," "))
B43: 8 | I43: =IF(C43="L",IF(F43-D43>0,F43-D43," "),IF(D43-F43>0,D43-F43," ")) | J43: =IF(C43="L",IF(F43-D43>0,(F43-D43)*200*E43," "),IF(D43-F43>0,(D43-F43)*200*E43," ")) | K43: =IF(C43="L",IF(F43-D43<0,F43-D43," "),IF(D43-F43<0,D43-F43," ")) | L43: =IF(C43="L",IF(F43-D43<0,(F43-D43)*200*E43," "),IF(D43-F43<0,(D43-F43)*200*E43," ")) | O43: Expected Return | R43: =IF(R39<0,((P37*P38/100)+(R37*R38/100)),P38) -> #DIV/0!
B44: 9 | I44: =IF(C44="L",IF(F44-D44>0,F44-D44," "),IF(D44-F44>0,D44-F44," ")) | J44: =IF(C44="L",IF(F44-D44>0,(F44-D44)*200*E44," "),IF(D44-F44>0,(D44-F44)*200*E44," ")) | K44: =IF(C44="L",IF(F44-D44<0,F44-D44," "),IF(D44-F44<0,D44-F44," ")) | L44: =IF(C44="L",IF(F44-D44<0,(F44-D44)*200*E44," "),IF(D44-F44<0,(D44-F44)*200*E44," "))
B45: 10 | I45: =IF(C45="L",IF(F45-D45>0,F45-D45," "),IF(D45-F45>0,D45-F45," ")) | J45: =IF(C45="L",IF(F45-D45>0,(F45-D45)*200*E45," "),IF(D45-F45>0,(D45-F45)*200*E45," ")) | K45: =IF(C45="L",IF(F45-D45<0,F45-D45," "),IF(D45-F45<0,D45-F45," ")) | L45: =IF(C45="L",IF(F45-D45<0,(F45-D45)*200*E45," "),IF(D45-F45<0,(D45-F45)*200*E45," "))
B46: 11 | I46: =IF(C46="L",IF(F46-D46>0,F46-D46," "),IF(D46-F46>0,D46-F46," ")) | J46: =IF(C46="L",IF(F46-D46>0,(F46-D46)*200*E46," "),IF(D46-F46>0,(D46-F46)*200*E46," ")) | K46: =IF(C46="L",IF(F46-D46<0,F46-D46," "),IF(D46-F46<0,D46-F46," ")) | L46: =IF(C46="L",IF(F46-D46<0,(F46-D46)*200*E46," "),IF(D46-F46<0,(D46-F46)*200*E46," ")) | O46: Top Ranking
B47: 12 | I47: =IF(C47="L",IF(F47-D47>0,F47-D47," "),IF(D47-F47>0,D47-F47," ")) | J47: =IF(C47="L",IF(F47-D47>0,(F47-D47)*200*E47," "),IF(D47-F47>0,(D47-F47)*200*E47," ")) | K47: =IF(C47="L",IF(F47-D47<0,F47-D47," "),IF(D47-F47<0,D47-F47," ")) | L47: =IF(C47="L",IF(F47-D47<0,(F47-D47)*200*E47," "),IF(D47-F47<0,(D47-F47)*200*E47," ")) | O47: Best Gain | P47: =MAX(I36:I60) -> 0
B48: 13 | I48: =IF(C48="L",IF(F48-D48>0,F48-D48," "),IF(D48-F48>0,D48-F48," ")) | J48: =IF(C48="L",IF(F48-D48>0,(F48-D48)*200*E48," "),IF(D48-F48>0,(D48-F48)*200*E48," ")) | K48: =IF(C48="L",IF(F48-D48<0,F48-D48," "),IF(D48-F48<0,D48-F48," ")) | L48: =IF(C48="L",IF(F48-D48<0,(F48-D48)*200*E48," "),IF(D48-F48<0,(D48-F48)*200*E48," ")) | O48: Best Gain Amount | P48: =MAX(J36:J60) -> 0
B49: 14 | I49: =IF(C49="L",IF(F49-D49>0,F49-D49," "),IF(D49-F49>0,D49-F49," ")) | J49: =IF(C49="L",IF(F49-D49>0,(F49-D49)*200*E49," "),IF(D49-F49>0,(D49-F49)*200*E49," ")) | K49: =IF(C49="L",IF(F49-D49<0,F49-D49," "),IF(D49-F49<0,D49-F49," ")) | L49: =IF(C49="L",IF(F49-D49<0,(F49-D49)*200*E49," "),IF(D49-F49<0,(D49-F49)*200*E49," ")) | O49: Bad Loss | P49: =MIN(K36:K60) -> 0
B50: 15 | I50: =IF(C50="L",IF(F50-D50>0,F50-D50," "),IF(D50-F50>0,D50-F50," ")) | J50: =IF(C50="L",IF(F50-D50>0,(F50-D50)*200*E50," "),IF(D50-F50>0,(D50-F50)*200*E50," ")) | K50: =IF(C50="L",IF(F50-D50<0,F50-D50," "),IF(D50-F50<0,D50-F50," ")) | L50: =IF(C50="L",IF(F50-D50<0,(F50-D50)*200*E50," "),IF(D50-F50<0,(D50-F50)*200*E50," ")) | O50: Bad Loss Amount | P50: =MIN(L36:L60) -> 0
B51: 16 | I51: =IF(C51="L",IF(F51-D51>0,F51-D51," "),IF(D51-F51>0,D51-F51," ")) | J51: =IF(C51="L",IF(F51-D51>0,(F51-D51)*200*E51," "),IF(D51-F51>0,(D51-F51)*200*E51," ")) | K51: =IF(C51="L",IF(F51-D51<0,F51-D51," "),IF(D51-F51<0,D51-F51," ")) | L51: =IF(C51="L",IF(F51-D51<0,(F51-D51)*200*E51," "),IF(D51-F51<0,(D51-F51)*200*E51," "))
B52: 17 | I52: =IF(C52="L",IF(F52-D52>0,F52-D52," "),IF(D52-F52>0,D52-F52," ")) | J52: =IF(C52="L",IF(F52-D52>0,(F52-D52)*200*E52," "),IF(D52-F52>0,(D52-F52)*200*E52," ")) | K52: =IF(C52="L",IF(F52-D52<0,F52-D52," "),IF(D52-F52<0,D52-F52," ")) | L52: =IF(C52="L",IF(F52-D52<0,(F52-D52)*200*E52," "),IF(D52-F52<0,(D52-F52)*200*E52," "))
B53: 18 | I53: =IF(C53="L",IF(F53-D53>0,F53-D53," "),IF(D53-F53>0,D53-F53," ")) | J53: =IF(C53="L",IF(F53-D53>0,(F53-D53)*200*E53," "),IF(D53-F53>0,(D53-F53)*200*E53," ")) | K53: =IF(C53="L",IF(F53-D53<0,F53-D53," "),IF(D53-F53<0,D53-F53," ")) | L53: =IF(C53="L",IF(F53-D53<0,(F53-D53)*200*E53," "),IF(D53-F53<0,(D53-F53)*200*E53," "))
B54: 19 | I54: =IF(C54="L",IF(F54-D54>0,F54-D54," "),IF(D54-F54>0,D54-F54," ")) | J54: =IF(C54="L",IF(F54-D54>0,(F54-D54)*200*E54," "),IF(D54-F54>0,(D54-F54)*200*E54," ")) | K54: =IF(C54="L",IF(F54-D54<0,F54-D54," "),IF(D54-F54<0,D54-F54," ")) | L54: =IF(C54="L",IF(F54-D54<0,(F54-D54)*200*E54," "),IF(D54-F54<0,(D54-F54)*200*E54," "))
B55: 20 | I55: =IF(C55="L",IF(F55-D55>0,F55-D55," "),IF(D55-F55>0,D55-F55," ")) | J55: =IF(C55="L",IF(F55-D55>0,(F55-D55)*200*E55," "),IF(D55-F55>0,(D55-F55)*200*E55," ")) | K55: =IF(C55="L",IF(F55-D55<0,F55-D55," "),IF(D55-F55<0,D55-F55," ")) | L55: =IF(C55="L",IF(F55-D55<0,(F55-D55)*200*E55," "),IF(D55-F55<0,(D55-F55)*200*E55," "))
B56: 21 | I56: =IF(C56="L",IF(F56-D56>0,F56-D56," "),IF(D56-F56>0,D56-F56," ")) | J56: =IF(C56="L",IF(F56-D56>0,(F56-D56)*200*E56," "),IF(D56-F56>0,(D56-F56)*200*E56," ")) | K56: =IF(C56="L",IF(F56-D56<0,F56-D56," "),IF(D56-F56<0,D56-F56," ")) | L56: =IF(C56="L",IF(F56-D56<0,(F56-D56)*200*E56," "),IF(D56-F56<0,(D56-F56)*200*E56," "))
B57: 22 | I57: =IF(C57="L",IF(F57-D57>0,F57-D57," "),IF(D57-F57>0,D57-F57," ")) | J57: =IF(C57="L",IF(F57-D57>0,(F57-D57)*200*E57," "),IF(D57-F57>0,(D57-F57)*200*E57," ")) | K57: =IF(C57="L",IF(F57-D57<0,F57-D57," "),IF(D57-F57<0,D57-F57," ")) | L57: =IF(C57="L",IF(F57-D57<0,(F57-D57)*200*E57," "),IF(D57-F57<0,(D57-F57)*200*E57," "))
B58: 23 | I58: =IF(C58="L",IF(F58-D58>0,F58-D58," "),IF(D58-F58>0,D58-F58," ")) | J58: =IF(C58="L",IF(F58-D58>0,(F58-D58)*200*E58," "),IF(D58-F58>0,(D58-F58)*200*E58," ")) | K58: =IF(C58="L",IF(F58-D58<0,F58-D58," "),IF(D58-F58<0,D58-F58," ")) | L58: =IF(C58="L",IF(F58-D58<0,(F58-D58)*200*E58," "),IF(D58-F58<0,(D58-F58)*200*E58," "))
B59: 24 | I59: =IF(C59="L",IF(F59-D59>0,F59-D59," "),IF(D59-F59>0,D59-F59," ")) | J59: =IF(C59="L",IF(F59-D59>0,(F59-D59)*200*E59," "),IF(D59-F59>0,(D59-F59)*200*E59," ")) | K59: =IF(C59="L",IF(F59-D59<0,F59-D59," "),IF(D59-F59<0,D59-F59," ")) | L59: =IF(C59="L",IF(F59-D59<0,(F59-D59)*200*E59," "),IF(D59-F59<0,(D59-F59)*200*E59," "))
B60: 25 | I60: =IF(C60="L",IF(F60-D60>0,F60-D60," "),IF(D60-F60>0,D60-F60," ")) | J60: =IF(C60="L",IF(F60-D60>0,(F60-D60)*200*E60," "),IF(D60-F60>0,(D60-F60)*200*E60," ")) | K60: =IF(C60="L",IF(F60-D60<0,F60-D60," "),IF(D60-F60<0,D60-F60," ")) | L60: =IF(C60="L",IF(F60-D60<0,(F60-D60)*200*E60," "),IF(D60-F60<0,(D60-F60)*200*E60," "))
A61: calculate | B61: =COUNT(I36:I60) -> 0 | C61: =COUNT(K36:K60) -> 0 | D61: =SUM(E36:E60)*2 -> 0 | I61: Commission per CON | K61: Com & Vat
I62: =I30 -> 15 | K62: =I62*D61*1.07 -> 0
A66: Open | F66: Close | I66: Gain | K66: Loss | O66: Score Board
A67: Date | B67: Order | C67: Side | D67: Price | E67: Volume | F67: Price | I67: จุด | J67: Amount | K67: จุด | L67: Amount | O67: Accuracy & Gain/Loss perform
A68: 42370 | B68: 1 | I68: =IF(C68="L",IF(F68-D68>0,F68-D68," "),IF(D68-F68>0,D68-F68," ")) | J68: =IF(C68="L",IF(F68-D68>0,(F68-D68)*200*E68," "),IF(D68-F68>0,(D68-F68)*200*E68," ")) | K68: =IF(C68="L",IF(F68-D68<0,F68-D68," "),IF(D68-F68<0,D68-F68," ")) | L68: =IF(C68="L",IF(F68-D68<0,(F68-D68)*200*E68," "),IF(D68-F68<0,(D68-F68)*200*E68," ")) | O68: Total Trade | P68: =B93+C93 -> 0
B69: 2 | I69: =IF(C69="L",IF(F69-D69>0,F69-D69," "),IF(D69-F69>0,D69-F69," ")) | J69: =IF(C69="L",IF(F69-D69>0,(F69-D69)*200*E69," "),IF(D69-F69>0,(D69-F69)*200*E69," ")) | K69: =IF(C69="L",IF(F69-D69<0,F69-D69," "),IF(D69-F69<0,D69-F69," ")) | L69: =IF(C69="L",IF(F69-D69<0,(F69-D69)*200*E69," "),IF(D69-F69<0,(D69-F69)*200*E69," ")) | O69: Winning Chance | P69: =B93/P68*100 -> #DIV/0! | Q69: Loss Chance | R69: =C93/P68*100 -> #DIV/0!
B70: 3 | I70: =IF(C70="L",IF(F70-D70>0,F70-D70," "),IF(D70-F70>0,D70-F70," ")) | J70: =IF(C70="L",IF(F70-D70>0,(F70-D70)*200*E70," "),IF(D70-F70>0,(D70-F70)*200*E70," ")) | K70: =IF(C70="L",IF(F70-D70<0,F70-D70," "),IF(D70-F70<0,D70-F70," ")) | L70: =IF(C70="L",IF(F70-D70<0,(F70-D70)*200*E70," "),IF(D70-F70<0,(D70-F70)*200*E70," ")) | O70: Average Gain | P70: =SUM(I68:I92)/B93 -> #DIV/0! | Q70: Average Loss | R70: =SUM(K68:K92)/C93 -> #DIV/0!
B71: 4 | I71: =IF(C71="L",IF(F71-D71>0,F71-D71," "),IF(D71-F71>0,D71-F71," ")) | J71: =IF(C71="L",IF(F71-D71>0,(F71-D71)*200*E71," "),IF(D71-F71>0,(D71-F71)*200*E71," ")) | K71: =IF(C71="L",IF(F71-D71<0,F71-D71," "),IF(D71-F71<0,D71-F71," ")) | L71: =IF(C71="L",IF(F71-D71<0,(F71-D71)*200*E71," "),IF(D71-F71<0,(D71-F71)*200*E71," ")) | O71: Total Gain | P71: =SUM(J68:J92) -> 0 | Q71: Total Loss | R71: =SUM(L68:L92) -> 0
B72: 5 | I72: =IF(C72="L",IF(F72-D72>0,F72-D72," "),IF(D72-F72>0,D72-F72," ")) | J72: =IF(C72="L",IF(F72-D72>0,(F72-D72)*200*E72," "),IF(D72-F72>0,(D72-F72)*200*E72," ")) | K72: =IF(C72="L",IF(F72-D72<0,F72-D72," "),IF(D72-F72<0,D72-F72," ")) | L72: =IF(C72="L",IF(F72-D72<0,(F72-D72)*200*E72," "),IF(D72-F72<0,(D72-F72)*200*E72," ")) | O72: Performance
B73: 6 | I73: =IF(C73="L",IF(F73-D73>0,F73-D73," "),IF(D73-F73>0,D73-F73," ")) | J73: =IF(C73="L",IF(F73-D73>0,(F73-D73)*200*E73," "),IF(D73-F73>0,(D73-F73)*200*E73," ")) | K73: =IF(C73="L",IF(F73-D73<0,F73-D73," "),IF(D73-F73<0,D73-F73," ")) | L73: =IF(C73="L",IF(F73-D73<0,(F73-D73)*200*E73," "),IF(D73-F73<0,(D73-F73)*200*E73," ")) | O73: Net Profit | P73: =P71+R71-K94 -> 0 | Q73: Cost rate | R73: =K94/P73 -> #DIV/0!
B74: 7 | I74: =IF(C74="L",IF(F74-D74>0,F74-D74," "),IF(D74-F74>0,D74-F74," ")) | J74: =IF(C74="L",IF(F74-D74>0,(F74-D74)*200*E74," "),IF(D74-F74>0,(D74-F74)*200*E74," ")) | K74: =IF(C74="L",IF(F74-D74<0,F74-D74," "),IF(D74-F74<0,D74-F74," ")) | L74: =IF(C74="L",IF(F74-D74<0,(F74-D74)*200*E74," "),IF(D74-F74<0,(D74-F74)*200*E74," "))
B75: 8 | I75: =IF(C75="L",IF(F75-D75>0,F75-D75," "),IF(D75-F75>0,D75-F75," ")) | J75: =IF(C75="L",IF(F75-D75>0,(F75-D75)*200*E75," "),IF(D75-F75>0,(D75-F75)*200*E75," ")) | K75: =IF(C75="L",IF(F75-D75<0,F75-D75," "),IF(D75-F75<0,D75-F75," ")) | L75: =IF(C75="L",IF(F75-D75<0,(F75-D75)*200*E75," "),IF(D75-F75<0,(D75-F75)*200*E75," ")) | O75: Expected Return | R75: =IF(R71<0,((P69*P70/100)+(R69*R70/100)),P70) -> #DIV/0!
B76: 9 | I76: =IF(C76="L",IF(F76-D76>0,F76-D76," "),IF(D76-F76>0,D76-F76," ")) | J76: =IF(C76="L",IF(F76-D76>0,(F76-D76)*200*E76," "),IF(D76-F76>0,(D76-F76)*200*E76," ")) | K76: =IF(C76="L",IF(F76-D76<0,F76-D76," "),IF(D76-F76<0,D76-F76," ")) | L76: =IF(C76="L",IF(F76-D76<0,(F76-D76)*200*E76," "),IF(D76-F76<0,(D76-F76)*200*E76," "))
B77: 10 | I77: =IF(C77="L",IF(F77-D77>0,F77-D77," "),IF(D77-F77>0,D77-F77," ")) | J77: =IF(C77="L",IF(F77-D77>0,(F77-D77)*200*E77," "),IF(D77-F77>0,(D77-F77)*200*E77," ")) | K77: =IF(C77="L",IF(F77-D77<0,F77-D77," "),IF(D77-F77<0,D77-F77," ")) | L77: =IF(C77="L",IF(F77-D77<0,(F77-D77)*200*E77," "),IF(D77-F77<0,(D77-F77)*200*E77," "))
B78: 11 | I78: =IF(C78="L",IF(F78-D78>0,F78-D78," "),IF(D78-F78>0,D78-F78," ")) | J78: =IF(C78="L",IF(F78-D78>0,(F78-D78)*200*E78," "),IF(D78-F78>0,(D78-F78)*200*E78," ")) | K78: =IF(C78="L",IF(F78-D78<0,F78-D78," "),IF(D78-F78<0,D78-F78," ")) | L78: =IF(C78="L",IF(F78-D78<0,(F78-D78)*200*E78," "),IF(D78-F78<0,(D78-F78)*200*E78," ")) | O78: Top Ranking
B79: 12 | I79: =IF(C79="L",IF(F79-D79>0,F79-D79," "),IF(D79-F79>0,D79-F79," ")) | J79: =IF(C79="L",IF(F79-D79>0,(F79-D79)*200*E79," "),IF(D79-F79>0,(D79-F79)*200*E79," ")) | K79: =IF(C79="L",IF(F79-D79<0,F79-D79," "),IF(D79-F79<0,D79-F79," ")) | L79: =IF(C79="L",IF(F79-D79<0,(F79-D79)*200*E79," "),IF(D79-F79<0,(D79-F79)*200*E79," ")) | O79: Best Gain | P79: =MAX(I68:I92) -> 0
B80: 13 | I80: =IF(C80="L",IF(F80-D80>0,F80-D80," "),IF(D80-F80>0,D80-F80," ")) | J80: =IF(C80="L",IF(F80-D80>0,(F80-D80)*200*E80," "),IF(D80-F80>0,(D80-F80)*200*E80," ")) | K80: =IF(C80="L",IF(F80-D80<0,F80-D80," "),IF(D80-F80<0,D80-F80," ")) | L80: =IF(C80="L",IF(F80-D80<0,(F80-D80)*200*E80," "),IF(D80-F80<0,(D80-F80)*200*E80," ")) | O80: Best Gain Amount | P80: =MAX(J68:J92) -> 0
B81: 14 | I81: =IF(C81="L",IF(F81-D81>0,F81-D81," "),IF(D81-F81>0,D81-F81," ")) | J81: =IF(C81="L",IF(F81-D81>0,(F81-D81)*200*E81," "),IF(D81-F81>0,(D81-F81)*200*E81," ")) | K81: =IF(C81="L",IF(F81-D81<0,F81-D81," "),IF(D81-F81<0,D81-F81," ")) | L81: =IF(C81="L",IF(F81-D81<0,(F81-D81)*200*E81," "),IF(D81-F81<0,(D81-F81)*200*E81," ")) | O81: Bad Loss | P81: =MIN(K68:K92) -> 0
B82: 15 | I82: =IF(C82="L",IF(F82-D82>0,F82-D82," "),IF(D82-F82>0,D82-F82," ")) | J82: =IF(C82="L",IF(F82-D82>0,(F82-D82)*200*E82," "),IF(D82-F82>0,(D82-F82)*200*E82," ")) | K82: =IF(C82="L",IF(F82-D82<0,F82-D82," "),IF(D82-F82<0,D82-F82," ")) | L82: =IF(C82="L",IF(F82-D82<0,(F82-D82)*200*E82," "),IF(D82-F82<0,(D82-F82)*200*E82," ")) | O82: Bad Loss Amount | P82: =MIN(L68:L92) -> 0
B83: 16 | I83: =IF(C83="L",IF(F83-D83>0,F83-D83," "),IF(D83-F83>0,D83-F83," ")) | J83: =IF(C83="L",IF(F83-D83>0,(F83-D83)*200*E83," "),IF(D83-F83>0,(D83-F83)*200*E83," ")) | K83: =IF(C83="L",IF(F83-D83<0,F83-D83," "),IF(D83-F83<0,D83-F83," ")) | L83: =IF(C83="L",IF(F83-D83<0,(F83-D83)*200*E83," "),IF(D83-F83<0,(D83-F83)*200*E83," "))
B84: 17 | I84: =IF(C84="L",IF(F84-D84>0,F84-D84," "),IF(D84-F84>0,D84-F84," ")) | J84: =IF(C84="L",IF(F84-D84>0,(F84-D84)*200*E84," "),IF(D84-F84>0,(D84-F84)*200*E84," ")) | K84: =IF(C84="L",IF(F84-D84<0,F84-D84," "),IF(D84-F84<0,D84-F84," ")) | L84: =IF(C84="L",IF(F84-D84<0,(F84-D84)*200*E84," "),IF(D84-F84<0,(D84-F84)*200*E84," "))
B85: 18 | I85: =IF(C85="L",IF(F85-D85>0,F85-D85," "),IF(D85-F85>0,D85-F85," ")) | J85: =IF(C85="L",IF(F85-D85>0,(F85-D85)*200*E85," "),IF(D85-F85>0,(D85-F85)*200*E85," ")) | K85: =IF(C85="L",IF(F85-D85<0,F85-D85," "),IF(D85-F85<0,D85-F85," ")) | L85: =IF(C85="L",IF(F85-D85<0,(F85-D85)*200*E85," "),IF(D85-F85<0,(D85-F85)*200*E85," "))
B86: 19 | I86: =IF(C86="L",IF(F86-D86>0,F86-D86," "),IF(D86-F86>0,D86-F86," ")) | J86: =IF(C86="L",IF(F86-D86>0,(F86-D86)*200*E86," "),IF(D86-F86>0,(D86-F86)*200*E86," ")) | K86: =IF(C86="L",IF(F86-D86<0,F86-D86," "),IF(D86-F86<0,D86-F86," ")) | L86: =IF(C86="L",IF(F86-D86<0,(F86-D86)*200*E86," "),IF(D86-F86<0,(D86-F86)*200*E86," "))
B87: 20 | I87: =IF(C87="L",IF(F87-D87>0,F87-D87," "),IF(D87-F87>0,D87-F87," ")) | J87: =IF(C87="L",IF(F87-D87>0,(F87-D87)*200*E87," "),IF(D87-F87>0,(D87-F87)*200*E87," ")) | K87: =IF(C87="L",IF(F87-D87<0,F87-D87," "),IF(D87-F87<0,D87-F87," ")) | L87: =IF(C87="L",IF(F87-D87<0,(F87-D87)*200*E87," "),IF(D87-F87<0,(D87-F87)*200*E87," "))
B88: 21 | I88: =IF(C88="L",IF(F88-D88>0,F88-D88," "),IF(D88-F88>0,D88-F88," ")) | J88: =IF(C88="L",IF(F88-D88>0,(F88-D88)*200*E88," "),IF(D88-F88>0,(D88-F88)*200*E88," ")) | K88: =IF(C88="L",IF(F88-D88<0,F88-D88," "),IF(D88-F88<0,D88-F88," ")) | L88: =IF(C88="L",IF(F88-D88<0,(F88-D88)*200*E88," "),IF(D88-F88<0,(D88-F88)*200*E88," "))
B89: 22 | I89: =IF(C89="L",IF(F89-D89>0,F89-D89," "),IF(D89-F89>0,D89-F89," ")) | J89: =IF(C89="L",IF(F89-D89>0,(F89-D89)*200*E89," "),IF(D89-F89>0,(D89-F89)*200*E89," ")) | K89: =IF(C89="L",IF(F89-D89<0,F89-D89," "),IF(D89-F89<0,D89-F89," ")) | L89: =IF(C89="L",IF(F89-D89<0,(F89-D89)*200*E89," "),IF(D89-F89<0,(D89-F89)*200*E89," "))
B90: 23 | I90: =IF(C90="L",IF(F90-D90>0,F90-D90," "),IF(D90-F90>0,D90-F90," ")) | J90: =IF(C90="L",IF(F90-D90>0,(F90-D90)*200*E90," "),IF(D90-F90>0,(D90-F90)*200*E90," ")) | K90: =IF(C90="L",IF(F90-D90<0,F90-D90," "),IF(D90-F90<0,D90-F90," ")) | L90: =IF(C90="L",IF(F90-D90<0,(F90-D90)*200*E90," "),IF(D90-F90<0,(D90-F90)*200*E90," "))
B91: 24 | I91: =IF(C91="L",IF(F91-D91>0,F91-D91," "),IF(D91-F91>0,D91-F91," ")) | J91: =IF(C91="L",IF(F91-D91>0,(F91-D91)*200*E91," "),IF(D91-F91>0,(D91-F91)*200*E91," ")) | K91: =IF(C91="L",IF(F91-D91<0,F91-D91," "),IF(D91-F91<0,D91-F91," ")) | L91: =IF(C91="L",IF(F91-D91<0,(F91-D91)*200*E91," "),IF(D91-F91<0,(D91-F91)*200*E91," "))
B92: 25 | I92: =IF(C92="L",IF(F92-D92>0,F92-D92," "),IF(D92-F92>0,D92-F92," ")) | J92: =IF(C92="L",IF(F92-D92>0,(F92-D92)*200*E92," "),IF(D92-F92>0,(D92-F92)*200*E92," ")) | K92: =IF(C92="L",IF(F92-D92<0,F92-D92," "),IF(D92-F92<0,D92-F92," ")) | L92: =IF(C92="L",IF(F92-D92<0,(F92-D92)*200*E92," "),IF(D92-F92<0,(D92-F92)*200*E92," "))
A93: calculate | B93: =COUNT(I68:I92) -> 0 | C93: =COUNT(K68:K92) -> 0 | D93: =SUM(E68:E92)*2 -> 0 | I93: Commission per CON | K93: Com & Vat
I94: =I62 -> 15 | K94: =I94*D93*1.07 -> 0
A98: Open | F98: Close | I98: Gain | K98: Loss | O98: Score Board
A99: Date | B99: Order | C99: Side | D99: Price | E99: Volume | F99: Price | I99: จุด | J99: Amount | K99: จุด | L99: Amount | O99: Accuracy & Gain/Loss perform
A100: 42370 | B100: 1 | I100: =IF(C100="L",IF(F100-D100>0,F100-D100," "),IF(D100-F100>0,D100-F100," ")) | J100: =IF(C100="L",IF(F100-D100>0,(F100-D100)*200*E100," "),IF(D100-F100>0,(D100-F100)*200*E100," ")) | K100: =IF(C100="L",IF(F100-D100<0,F100-D100," "),IF(D100-F100<0,D100-F100," ")) | L100: =IF(C100="L",IF(F100-D100<0,(F100-D100)*200*E100," "),IF(D100-F100<0,(D100-F100)*200*E100," ")) | O100: Total Trade | P100: =B125+C125 -> 0
B101: 2 | I101: =IF(C101="L",IF(F101-D101>0,F101-D101," "),IF(D101-F101>0,D101-F101," ")) | J101: =IF(C101="L",IF(F101-D101>0,(F101-D101)*200*E101," "),IF(D101-F101>0,(D101-F101)*200*E101," ")) | K101: =IF(C101="L",IF(F101-D101<0,F101-D101," "),IF(D101-F101<0,D101-F101," ")) | L101: =IF(C101="L",IF(F101-D101<0,(F101-D101)*200*E101," "),IF(D101-F101<0,(D101-F101)*200*E101," ")) | O101: Winning Chance | P101: =B125/P100*100 -> #DIV/0! | Q101: Loss Chance | R101: =C125/P100*100 -> #DIV/0!
B102: 3 | I102: =IF(C102="L",IF(F102-D102>0,F102-D102," "),IF(D102-F102>0,D102-F102," ")) | J102: =IF(C102="L",IF(F102-D102>0,(F102-D102)*200*E102," "),IF(D102-F102>0,(D102-F102)*200*E102," ")) | K102: =IF(C102="L",IF(F102-D102<0,F102-D102," "),IF(D102-F102<0,D102-F102," ")) | L102: =IF(C102="L",IF(F102-D102<0,(F102-D102)*200*E102," "),IF(D102-F102<0,(D102-F102)*200*E102," ")) | O102: Average Gain | P102: =SUM(I100:I124)/B125 -> #DIV/0! | Q102: Average Loss | R102: =SUM(K100:K124)/C125 -> #DIV/0!
B103: 4 | I103: =IF(C103="L",IF(F103-D103>0,F103-D103," "),IF(D103-F103>0,D103-F103," ")) | J103: =IF(C103="L",IF(F103-D103>0,(F103-D103)*200*E103," "),IF(D103-F103>0,(D103-F103)*200*E103," ")) | K103: =IF(C103="L",IF(F103-D103<0,F103-D103," "),IF(D103-F103<0,D103-F103," ")) | L103: =IF(C103="L",IF(F103-D103<0,(F103-D103)*200*E103," "),IF(D103-F103<0,(D103-F103)*200*E103," ")) | O103: Total Gain | P103: =SUM(J100:J124) -> 0 | Q103: Total Loss | R103: =SUM(L100:L124) -> 0
B104: 5 | I104: =IF(C104="L",IF(F104-D104>0,F104-D104," "),IF(D104-F104>0,D104-F104," ")) | J104: =IF(C104="L",IF(F104-D104>0,(F104-D104)*200*E104," "),IF(D104-F104>0,(D104-F104)*200*E104," ")) | K104: =IF(C104="L",IF(F104-D104<0,F104-D104," "),IF(D104-F104<0,D104-F104," ")) | L104: =IF(C104="L",IF(F104-D104<0,(F104-D104)*200*E104," "),IF(D104-F104<0,(D104-F104)*200*E104," ")) | O104: Performance
B105: 6 | I105: =IF(C105="L",IF(F105-D105>0,F105-D105," "),IF(D105-F105>0,D105-F105," ")) | J105: =IF(C105="L",IF(F105-D105>0,(F105-D105)*200*E105," "),IF(D105-F105>0,(D105-F105)*200*E105," ")) | K105: =IF(C105="L",IF(F105-D105<0,F105-D105," "),IF(D105-F105<0,D105-F105," ")) | L105: =IF(C105="L",IF(F105-D105<0,(F105-D105)*200*E105," "),IF(D105-F105<0,(D105-F105)*200*E105," ")) | O105: Net Profit | P105: =P103+R103-K126 -> 0 | Q105: Cost rate | R105: =K126/P105 -> #DIV/0!
B106: 7 | I106: =IF(C106="L",IF(F106-D106>0,F106-D106," "),IF(D106-F106>0,D106-F106," ")) | J106: =IF(C106="L",IF(F106-D106>0,(F106-D106)*200*E106," "),IF(D106-F106>0,(D106-F106)*200*E106," ")) | K106: =IF(C106="L",IF(F106-D106<0,F106-D106," "),IF(D106-F106<0,D106-F106," ")) | L106: =IF(C106="L",IF(F106-D106<0,(F106-D106)*200*E106," "),IF(D106-F106<0,(D106-F106)*200*E106," "))
B107: 8 | I107: =IF(C107="L",IF(F107-D107>0,F107-D107," "),IF(D107-F107>0,D107-F107," ")) | J107: =IF(C107="L",IF(F107-D107>0,(F107-D107)*200*E107," "),IF(D107-F107>0,(D107-F107)*200*E107," ")) | K107: =IF(C107="L",IF(F107-D107<0,F107-D107," "),IF(D107-F107<0,D107-F107," ")) | L107: =IF(C107="L",IF(F107-D107<0,(F107-D107)*200*E107," "),IF(D107-F107<0,(D107-F107)*200*E107," ")) | O107: Expected Return | R107: =IF(R103<0,((P101*P102/100)+(R101*R102/100)),P102) -> #DIV/0!
B108: 9 | I108: =IF(C108="L",IF(F108-D108>0,F108-D108," "),IF(D108-F108>0,D108-F108," ")) | J108: =IF(C108="L",IF(F108-D108>0,(F108-D108)*200*E108," "),IF(D108-F108>0,(D108-F108)*200*E108," ")) | K108: =IF(C108="L",IF(F108-D108<0,F108-D108," "),IF(D108-F108<0,D108-F108," ")) | L108: =IF(C108="L",IF(F108-D108<0,(F108-D108)*200*E108," "),IF(D108-F108<0,(D108-F108)*200*E108," "))
B109: 10 | I109: =IF(C109="L",IF(F109-D109>0,F109-D109," "),IF(D109-F109>0,D109-F109," ")) | J109: =IF(C109="L",IF(F109-D109>0,(F109-D109)*200*E109," "),IF(D109-F109>0,(D109-F109)*200*E109," ")) | K109: =IF(C109="L",IF(F109-D109<0,F109-D109," "),IF(D109-F109<0,D109-F109," ")) | L109: =IF(C109="L",IF(F109-D109<0,(F109-D109)*200*E109," "),IF(D109-F109<0,(D109-F109)*200*E109," "))
...

Sheet Graph
A1: port | B1: win%
A2: =Record!K1+Record!P9 -> 18067.9 | B2: =Record!P5 -> 100
A3: =A2+Record!P41 -> 18067.9 | B3: =Record!P37 -> #DIV/0!
A4: =A3+Record!P73 -> 18067.9 | B4: =Record!P69 -> #DIV/0!
A5: =A4+Record!P105 -> 18067.9 | B5: =Record!P101 -> #DIV/0!
A6: =A5+Record!P137 -> 18067.9 | B6: =Record!P133 -> #DIV/0!
A7: =A6+Record!P169 -> 18067.9 | B7: =Record!P165 -> #DIV/0!
A8: =A7+Record!P201 -> 18067.9 | B8: =Record!P197 -> #DIV/0!
A9: =A8+Record!P233 -> 18067.9 | B9: =Record!P229 -> #DIV/0!
A10: =A9+Record!P265 -> 18067.9 | B10: =Record!P261 -> #DIV/0!
A11: =A10+Record!P297 -> 18067.9 | B11: =Record!P293 -> #DIV/0!
A12: =A11+Record!P329 -> 18067.9 | B12: =Record!P325 -> #DIV/0!
A13: =A12+Record!P361 -> 18067.9 | B13: =Record!P357 -> #DIV/0!
A14: =A13+Record!P393 -> 18067.9 | B14: =Record!P389 -> #DIV/0!
A15: =A14+Record!P425 -> 18067.9 | B15: =Record!P421 -> #DIV/0!
A16: =A15+Record!P457 -> 18067.9 | B16: =Record!P453 -> #DIV/0!
A17: =A16+Record!P489 -> 18067.9 | B17: =Record!P485 -> #DIV/0!
A18: =A17+Record!P521 -> 18067.9 | B18: =Record!P517 -> #DIV/0!
A19: =A18+Record!P553 -> 18067.9 | B19: =Record!P549 -> #DIV/0!
A20: =A19+Record!P585 -> 18067.9 | B20: =Record!P581 -> #DIV/0!
A21: =A20+Record!P617 -> 18067.9 | B21: =Record!P613 -> #DIV/0!
A22: =A21+Record!P649 -> 18067.9 | B22: =Record!P645 -> #DIV/0!
A23: =A22+Record!P681 -> 18067.9 | B23: =Record!P677 -> #DIV/0!
A24: =A23+Record!P713 -> 18067.9 | B24: =Record!P709 -> #DIV/0!
A25: =A24+Record!P745 -> 18067.9 | B25: =Record!P741 -> #DIV/0!
A26: =A25+Record!P777 -> 18067.9 | B26: =Record!P773 -> #DIV/0!
A27: =A26+Record!P809 -> 18067.9 | B27: =Record!P805 -> #DIV/0!
A29: ex r | B29: avg gain
A30: =Record!R11 -> 0 | B30: =Record!P6 -> 0
A31: =Record!R43 -> #DIV/0! | B31: =Record!P38 -> #DIV/0!
A32: =Record!R75 -> #DIV/0! | B32: =Record!P70 -> #DIV/0!
A33: =Record!R107 -> #DIV/0! | B33: =Record!P102 -> #DIV/0!
A34: =Record!R139 -> #DIV/0! | B34: =Record!P134 -> #DIV/0!
A35: =Record!R171 -> #DIV/0! | B35: =Record!P166 -> #DIV/0!
A36: =Record!R203 -> #DIV/0! | B36: =Record!P198 -> #DIV/0!
A37: =Record!R235 -> #DIV/0! | B37: =Record!P230 -> #DIV/0!
A38: =Record!R267 -> #DIV/0! | B38: =Record!P262 -> #DIV/0!
A39: =Record!R299 -> #DIV/0! | B39: =Record!P294 -> #DIV/0!
A40: =Record!R331 -> #DIV/0! | B40: =Record!P326 -> #DIV/0!
A41: =Record!R363 -> #DIV/0! | B41: =Record!P358 -> #DIV/0!
A42: =Record!R395 -> #DIV/0! | B42: =Record!P390 -> #DIV/0!
A43: =Record!R427 -> #DIV/0! | B43: =Record!P422 -> #DIV/0!
A44: =Record!R459 -> #DIV/0! | B44: =Record!P454 -> #DIV/0!
A45: =Record!R491 -> #DIV/0! | B45: =Record!P486 -> #DIV/0!
A46: =Record!R523 -> #DIV/0! | B46: =Record!P518 -> #DIV/0!
A47: =Record!R555 -> #DIV/0! | B47: =Record!P550 -> #DIV/0!
A48: =Record!R587 -> #DIV/0! | B48: =Record!P582 -> #DIV/0!
A49: =Record!R619 -> #DIV/0! | B49: =Record!P614 -> #DIV/0!
A50: =Record!R651 -> #DIV/0! | B50: =Record!P646 -> #DIV/0!
A51: =Record!R683 -> #DIV/0! | B51: =Record!P678 -> #DIV/0!
A52: =Record!R715 -> #DIV/0! | B52: =Record!P710 -> #DIV/0!
A53: =Record!R747 -> #DIV/0! | B53: =Record!P742 -> #DIV/0!
A54: =Record!R779 -> #DIV/0! | B54: =Record!P774 -> #DIV/0!
A55: =Record!R811 -> #DIV/0! | B55: =Record!P806 -> #DIV/0!
A57: profit
A58: =Record!P9 -> 3067.9 | B58: 50
A59: =Record!P41 -> 0 | B59: 50
A60: =Record!P73 -> 0 | B60: 50
A61: =Record!P105 -> 0 | B61: 50
A62: =Record!P137 -> 0 | B62: 50
A63: =Record!P169 -> 0 | B63: 50
A64: =Record!P201 -> 0 | B64: 50
A65: =Record!P233 -> 0 | B65: 50
A66: =Record!P265 -> 0 | B66: 50
A67: =Record!P297 -> 0 | B67: 50
A68: =Record!P329 -> 0 | B68: 50
A69: =Record!P361 -> 0 | B69: 50
A70: =Record!P393 -> 0 | B70: 50
A71: =Record!P425 -> 0 | B71: 50
A72: =Record!P457 -> 0 | B72: 50
A73: =Record!P489 -> 0 | B73: 50
A74: =Record!P521 -> 0 | B74: 50
A75: =Record!P553 -> 0 | B75: 50
A76: =Record!P585 -> 0 | B76: 50
A77: =Record!P617 -> 0 | B77: 50
A78: =Record!P649 -> 0 | B78: 50
A79: =Record!P681 -> 0 | B79: 50
A80: =Record!P713 -> 0 | B80: 50
A81: =Record!P745 -> 0 | B81: 50
A82: =Record!P777 -> 0 | B82: 50
A83: =Record!P809 -> 0 | B83: 50

Sheet Sheet3
